ecmind_blue_client_manage/__init__.py
ecmind_blue_client_manage/access.py
ecmind_blue_client_manage/manage.py
ecmind_blue_client_manage/system_role.py
ecmind_blue_client_manage-0.2.1.dist-info/LICENSE
ecmind_blue_client_manage-0.2.1.dist-info/METADATA
ecmind_blue_client_manage-0.2.1.dist-info/WHEEL
ecmind_blue_client_manage-0.2.1.dist-info/top_level.txt
ecmind_blue_client_manage-0.2.1.dist-info/RECORD
