Metadata-Version: 2.1
Name: ecmind-blue-client-manage
Version: 0.2.1
Summary: Helper modules for the `ecmind_blue_client` to ease the work with management APIs.
Home-page: https://gitlab.ecmind.ch/open/ecmind_blue_client_manage
Author: Roland Koller, Ulrich Wohlfeil & other contributers
Author-email: info@ecmind.ch
Classifier: Programming Language :: Python :: 3
Classifier: License :: OSI Approved :: MIT License
Classifier: Operating System :: OS Independent
Requires-Python: >=3.9
License-File: LICENSE
Requires-Dist: ecmind-blue-client (>=0.4.6)
Requires-Dist: XmlElement (>=0.3.1)
Requires-Dist: ftfy
